{"id":3014,"date":"2023-07-17T00:02:53","date_gmt":"2023-07-17T00:02:53","guid":{"rendered":"https:\/\/dev-ne-wrdprs-hepo.azurewebsites.net\/?p=3014"},"modified":"2023-07-17T00:02:53","modified_gmt":"2023-07-17T00:02:53","slug":"is-it-okay-if-she-hangs-out-with-another-guy","status":"publish","type":"post","link":"https:\/\/dev-ne-wrdprs-hepo.azurewebsites.net\/is-it-okay-if-she-hangs-out-with-another-guy\/","title":{"rendered":"Is-it Okay If She Hangs Out With Another Guy?"},"content":{"rendered":"<h2 class=\"hSubTitle\" itemprop=\"name\">\nShe&#8217;s Spending Time With Some Other Guys And You Are Envious &#8211; This Is What To Complete<\/h2>\n<\/p>\n<h3>Issue<\/h3>\n<\/p>\n<p style=\"\">\n<\/p>\n<h3>The Answer<\/h3>\n<p>Hi Insecure,<\/p>\n<p>Of all the uncomfortable aspects of getting a dude \u00e2\u0080\u0094 having your balls stuck to your leg, prostate cancer tumors, etcetera \u00e2\u0080\u0094 the absolute most tough is managing the dumb inner caveman. Do you know what i am talking about. You are an intelligent, refined person, but there is this primitive voice inside you. The vocals of a territorial, chest-beating idiot whoever entire frontal cortex has-been substituted for a large case of testosterone. This is actually the interior voice exactly who motivates all your valuable worst behavior \u00e2\u0080\u0094 leering for extended periods at every woman around you, bragging loudly about your achievements, and, more appropriate right here, getting thoughtlessly, indiscriminately jealous, set up circumstance warrants it.<\/p>\n<p>Everybody knows that, on some amount, we get a tiny bit consumed with stress when the sweetheart is actually hanging out with a handsome man. Your own eyeball simply begins to twitch quite. You wonder any time you could overcome him to a bloody pulp, in a-pinch. Essentially obtain territorial in an awful way. Your caveman brain is actually screaming at you \u00e2\u0080\u0094 your own caveman head claims you are in trouble, and you should respond instantly.<\/p>\n<p>And you have to share with that section of your mind to shut-up. Because, really, its feasible for you&#8217;re really dealing with some form of considerable connection situation right here. Maybe she actually is really considering cheating on you, or is just getting notably psychologically affixed. Prior to you decide that, you should employ your judgement. Impede. Actually consider the details. Notice that, if the girl doesn&#8217;t always have a single sensation with this guy beyond friendship, you will go off like an insecure douche should you decide inform the lady she should stop hanging out with him.<\/p>\n<p>Contemplate it. Do you want it should your girlfriend hassled you about yourself getting together with your female pals? Most likely not, correct? Might feel caged. Trapped. Resentful regarding the proven fact that you are needing to focus on your own girl&#8217;s childish neuroticism. Most likely, we aren&#8217;t in medieval times. People have buddies of genders.<\/p>\n<p>My advice, thus, is you you should not generate a hard and quick guideline about whether the girl can or can not go out with any male buddies. You must continue a situation by case basis. The suspicions might-be warranted. But, typically, you should research suspicions, perhaps not trust them instantly. Sometimes smoke indicates flame, but often smoke cigarettes only means a person&#8217;s puffing a large excess fat doobie. Your own intuition are worth paying attention to, however well worth instantly obeying. Truly study whether you can find any symptoms that she has a significant lady-boner because of this man, after that, if you feel she does, raise the subject.<\/p>\n<p>Additionally, another caveat i ought to add right here, that will be hard to just take, but basically, unfortuitously, true: having crushes when you are in a romantic union is incredibly regular. If you don&#8217;t&#8217;re both ugliest folks in the world, with fortuitously found both, you are both gonna encounter thoughts of connection to other people before you decide to pass away. Handling this is simply among the many much less enjoyable areas of any monogamous relationship. You should not throw a tantrum, do not instantly go to the nearest online dating <a href=\"https:\/\/www.milfdatingnetwork.com\/sugar-momma-dating.html\">visit sugar momma website site<\/a>.<\/p>\n<p>Just what does utilizing your judgement seem like? Don&#8217;t worry, it is not particularly tough \u00e2\u0080\u0094 you&#8217;re probably rather skilled in your gf&#8217;s behavior, and that means you know very well what it seems like whenever she is stoked up about somebody. Recall very first couple of times, together with lovable look on her behalf face whenever she noticed you across the bar. Recall just how your own laughs usually made her laugh, even though these weren&#8217;t funny anyway. Possibly she had been usually sort of suppressing a smile \u00e2\u0080\u0094 the sides of the woman lips were constantly tilting lightly up.<\/p>\n<p>Really does any of this occur if your girlfriend will get a text using this dude? Really does his existence create a greater calibre of pleasure than a brush with a dude pal usually does? Is actually she having difficulty keeping a straight face when she mentions him?<\/p>\n<p>Normally averagely important signs that there is one thing taking place. Nevertheless the more severe real question is whether she actually is getting questionable about him. Does she state she actually is getting together with \u00e2\u0080\u0098a buddy&#8217; in place of claiming his name? Any time you perhaps suggest the 3 people hang out with each other, is their timetable abruptly full?<\/p>\n<p>In the event the answers to a lot of these questions are \u00e2\u0080\u0098yeah&#8217; or \u00e2\u0080\u0098kinda seems like it&#8217;, then you certainly should really speak to your gf about any of it. Where I don&#8217;t indicate jeopardize to kill the guy involved. Or bang the shoe on the table, contact your own girlfriend a liar, and move all your valuable stuff out from the apartment. Relax. You should be one right here: assertive, confident, sensible. Only say, &#8220;Hey, i&#8217;m like we ought to discuss your own friendship with [insert name of knuckle-dragging, mouth-breathing idiot right here].&#8221;<\/p>\n<p>Actually, i have been in this case before \u00e2\u0080\u0094 on the other side. Yeah, I became &#8220;that guy.&#8221; My personal relationship with this particular lady Caroline was, well, a touch too good. She kept advising myself I smelled very nice, which will be a somewhat odd thing for an attached woman to express to an unattached man. We would end up being going out for coffee, but we might find yourself consuming at a great cafe together, which is not quite an ordinary platonic bro-down task. My emotions about the scenario had been conflicted. While I loved the interest, we realized everything was only a little dubious. One of two circumstances were gonna take place: our very own friendship was going to conclude, or her relationship.<\/p>\n<p>And I also need to provide the girl sweetheart credit score rating. He noticed what was happening, in which he contacted it in best way feasible. One-day, Caroline known as myself and mentioned, &#8220;Hey, therefore, Steve asserted that possibly all of our relationship gets a tad too close for comfort. The guy reliable myself once I asserted that absolutely nothing occurred, but he&#8217;s not totally pleased about us witnessing each other. Would it be OK if we failed to go out alone to any extent further? Or perhaps when it comes to near future?&#8221; That felt best that you me personally. I decided to those conditions.<\/p>\n<p>Resemble Steve. Go into this together with your head turned on and don&#8217;t panic. This might be an extremely typical moment of monogamous anxiety. It isn&#8217;t a problem. It&#8217;ll just escape hand any time you allow it.<\/p><\/p>\n","protected":false},"excerpt":{"rendered":"<p>She&#8217;s Spending Time With Some Other Guys And You Are Envious &#8211; This Is What To Complete Issue The Answer Hi Insecure, Of all the uncomfortable aspects of getting a dude \u00e2\u0080\u0094 having your balls stuck to your leg, prostate cancer tumors, etcetera \u00e2\u0080\u0094 the absolute most tough is managing the dumb inner caveman. Do &hellip;<\/p>\n<p class=\"read-more\"> <a class=\"\" href=\"https:\/\/dev-ne-wrdprs-hepo.azurewebsites.net\/is-it-okay-if-she-hangs-out-with-another-guy\/\"> <span class=\"screen-reader-text\">Is-it Okay If She Hangs Out With Another Guy?<\/span> Lire la suite\u00a0\u00bb<\/a><\/p>\n","protected":false},"author":4,"featured_media":0,"comment_status":"closed","ping_status":"open","sticky":false,"template":"","format":"standard","meta":{"_joinchat":[]},"categories":[7],"tags":[],"_links":{"self":[{"href":"https:\/\/dev-ne-wrdprs-hepo.azurewebsites.net\/wp-json\/wp\/v2\/posts\/3014"}],"collection":[{"href":"https:\/\/dev-ne-wrdprs-hepo.azurewebsites.net\/wp-json\/wp\/v2\/posts"}],"about":[{"href":"https:\/\/dev-ne-wrdprs-hepo.azurewebsites.net\/wp-json\/wp\/v2\/types\/post"}],"author":[{"embeddable":true,"href":"https:\/\/dev-ne-wrdprs-hepo.azurewebsites.net\/wp-json\/wp\/v2\/users\/4"}],"replies":[{"embeddable":true,"href":"https:\/\/dev-ne-wrdprs-hepo.azurewebsites.net\/wp-json\/wp\/v2\/comments?post=3014"}],"version-history":[{"count":1,"href":"https:\/\/dev-ne-wrdprs-hepo.azurewebsites.net\/wp-json\/wp\/v2\/posts\/3014\/revisions"}],"predecessor-version":[{"id":3015,"href":"https:\/\/dev-ne-wrdprs-hepo.azurewebsites.net\/wp-json\/wp\/v2\/posts\/3014\/revisions\/3015"}],"wp:attachment":[{"href":"https:\/\/dev-ne-wrdprs-hepo.azurewebsites.net\/wp-json\/wp\/v2\/media?parent=3014"}],"wp:term":[{"taxonomy":"category","embeddable":true,"href":"https:\/\/dev-ne-wrdprs-hepo.azurewebsites.net\/wp-json\/wp\/v2\/categories?post=3014"},{"taxonomy":"post_tag","embeddable":true,"href":"https:\/\/dev-ne-wrdprs-hepo.azurewebsites.net\/wp-json\/wp\/v2\/tags?post=3014"}],"curies":[{"name":"wp","href":"https:\/\/api.w.org\/{rel}","templated":true}]}}